LICENSE
MANIFEST.in
README.rst
pyproject.toml
setup.py
version.txt
bob/__init__.py
bob.devtools.egg-info/PKG-INFO
bob.devtools.egg-info/SOURCES.txt
bob.devtools.egg-info/dependency_links.txt
bob.devtools.egg-info/entry_points.txt
bob.devtools.egg-info/not-zip-safe
bob.devtools.egg-info/requires.txt
bob.devtools.egg-info/top_level.txt
bob/devtools/__init__.py
bob/devtools/bootstrap.py
bob/devtools/build.py
bob/devtools/changelog.py
bob/devtools/ci.py
bob/devtools/config.py
bob/devtools/constants.py
bob/devtools/dav.py
bob/devtools/deploy.py
bob/devtools/graph.py
bob/devtools/log.py
bob/devtools/mirror.py
bob/devtools/pipelines.py
bob/devtools/release.py
bob/devtools/test_bootstrap.py
bob/devtools/test_ci.py
bob/devtools/data/bobrc
bob/devtools/data/cacert.pem
bob/devtools/data/changelog_since_last_release.md
bob/devtools/data/conda_build_config.yaml
bob/devtools/data/matplotlibrc
bob/devtools/data/recipe_append.yaml
bob/devtools/data/gitlab-ci/beat-docker-package.yaml
bob/devtools/data/gitlab-ci/docs.yaml
bob/devtools/data/gitlab-ci/nightlies.yaml
bob/devtools/data/gitlab-ci/noarch.yaml
bob/devtools/data/gitlab-ci/python-package.yaml
bob/devtools/data/gitlab-ci/single-package.yaml
bob/devtools/scripts/__init__.py
bob/devtools/scripts/alternative_nightlies.py
bob/devtools/scripts/badges.py
bob/devtools/scripts/bdt.py
bob/devtools/scripts/build.py
bob/devtools/scripts/caupdate.py
bob/devtools/scripts/changelog.py
bob/devtools/scripts/ci.py
bob/devtools/scripts/commitfile.py
bob/devtools/scripts/common_options.py
bob/devtools/scripts/create.py
bob/devtools/scripts/dav.py
bob/devtools/scripts/dependencies.py
bob/devtools/scripts/development.py
bob/devtools/scripts/dumpsphinx.py
bob/devtools/scripts/getpath.py
bob/devtools/scripts/gitlab.py
bob/devtools/scripts/graph.py
bob/devtools/scripts/jobs.py
bob/devtools/scripts/lasttag.py
bob/devtools/scripts/local.py
bob/devtools/scripts/mirror.py
bob/devtools/scripts/new.py
bob/devtools/scripts/pipelines.py
bob/devtools/scripts/rebuild.py
bob/devtools/scripts/release.py
bob/devtools/scripts/runners.py
bob/devtools/scripts/settings.py
bob/devtools/scripts/sphinx.py
bob/devtools/scripts/test.py
bob/devtools/scripts/update_bob.py
bob/devtools/scripts/update_pins.py
