Metadata-Version: 2.1
Name: bob.devtools
Version: 5.4.2
Summary: Tools for development and CI integration of Bob/BEAT packages
Home-page: http://gitlab.idiap.ch/bob/bob.devtools
Author: Bob/BEAT Developers
Author-email: bob-devel@googlegroups.com,beat-devel@googlegroups.com
License: BSD
Classifier: Framework :: Bob
Classifier: Development Status :: 4 - Beta
Classifier: Intended Audience :: Developers
Classifier: License :: OSI Approved :: BSD License
Classifier: Natural Language :: English
Classifier: Programming Language :: Python
Classifier: Programming Language :: Python :: 3
Classifier: Topic :: Software Development :: Build Tools
License-File: LICENSE
